llmscout/__init__.py
llmscout/analyzer.py
llmscout/batch_downloader.py
llmscout/cli.py
llmscout/config.py
llmscout/crawler.py
llmscout/daily_fetch.py
llmscout/downloader.py
llmscout/generator.py
llmscout/logger.py
llmscout/pipeline.py
llmscout/utils.py
llmscout-0.1.0.dist-info/LICENSE
llmscout-0.1.0.dist-info/METADATA
llmscout-0.1.0.dist-info/WHEEL
llmscout-0.1.0.dist-info/entry_points.txt
llmscout-0.1.0.dist-info/top_level.txt
llmscout-0.1.0.dist-info/RECORD
