Metadata-Version: 2.2
Name: llmscout
Version: 0.1.0
Summary: An LLM-powered tool for discovering and analyzing research papers
Home-page: https://github.com/cafferychen777/llmscout
Author: Caffery Yang
Author-email: cafferychen777@gmail.com
Classifier: Development Status :: 3 - Alpha
Classifier: Intended Audience :: Science/Research
Classifier: License :: OSI Approved :: MIT License
Classifier: Operating System :: OS Independent
Classifier: Programming Language :: Python :: 3
Classifier: Programming Language :: Python :: 3.8
Classifier: Programming Language :: Python :: 3.9
Classifier: Programming Language :: Python :: 3.10
Classifier: Topic :: Scientific/Engineering :: Artificial Intelligence
Requires-Python: >=3.8
License-File: LICENSE
Requires-Dist: openai>=1.0.0
Requires-Dist: arxiv
Requires-Dist: pyyaml
Requires-Dist: pytz
Requires-Dist: requests>=2.31.0
Requires-Dist: python-dotenv>=1.0.0
Dynamic: author
Dynamic: author-email
Dynamic: classifier
Dynamic: description
Dynamic: description-content-type
Dynamic: home-page
Dynamic: requires-dist
Dynamic: requires-python
Dynamic: summary
